{"client":"Thunder Client","collectionName":"Abdullah Mert Ulusoy","dateExported":"2022-11-25T19:53:31.811Z","version":"1.1","folders":[],"requests":[{"_id":"b0674835-a12f-4e41-b832-de7fca57b85d","colId":"0e9db5e5-dc97-4ab4-bf4b-1bc9273b0090","containerId":"","name":"Mekan Ekle","url":"localhost:3000/api/mekanlar","method":"POST","sortNum":20000,"created":"2022-11-24T18:04:50.093Z","modified":"2022-11-24T18:31:44.374Z","headers":[],"params":[],"body":{"type":"formencoded","raw":"","form":[{"name":"ad","value":"Gloria Jeans"},{"name":"adres","value":"SDU Doğu Kampüsü"},{"name":"imkanlar","value":"Çay, Kahve, Kek"},{"name":"enlem","value":"37"},{"name":"boylam","value":"35"},{"name":"gunler1","value":"Pazartesi-Cuma"},{"name":"acilis1","value":"9:00"},{"name":"kapanis1","value":"23:00"},{"name":"kapali1","value":"false"},{"name":"gunler2","value":"Cumartesi"},{"name":"acilis2","value":"10:00"},{"name":"kapanis2","value":"17:00"},{"name":"kapali2","value":"true"}]},"tests":[]},{"_id":"b349be44-f1cb-4f9c-85a6-84a1706d215d","colId":"0e9db5e5-dc97-4ab4-bf4b-1bc9273b0090","containerId":"","name":"Mekanları Listele","url":"localhost:3000/api/mekanlar/?enlem=37.8&boylam=35.4","method":"GET","sortNum":30000,"created":"2022-11-24T18:05:04.402Z","modified":"2022-11-24T19:04:18.615Z","headers":[],"params":[{"name":"enlem","value":"37.8","isPath":false},{"name":"boylam","value":"35.4","isPath":false}],"tests":[]},{"_id":"99b6de37-ce7e-43f3-8225-c4e2fb5810dd","colId":"0e9db5e5-dc97-4ab4-bf4b-1bc9273b0090","containerId":"","name":"Mekan Getir","url":"localhost:3000/api/mekanlar/{{mekanid}}","method":"GET","sortNum":40000,"created":"2022-11-24T18:05:29.069Z","modified":"2022-11-25T19:17:55.153Z","headers":[],"params":[],"tests":[]},{"_id":"ae0e2e21-fc19-4b34-ade0-be78152339ec","colId":"0e9db5e5-dc97-4ab4-bf4b-1bc9273b0090","containerId":"","name":"Mekan Güncelle","url":"localhost:3000/api/mekanlar/{{mekanid}}","method":"PUT","sortNum":60000,"created":"2022-11-24T18:05:47.190Z","modified":"2022-11-25T19:34:53.903Z","headers":[],"params":[],"body":{"type":"formencoded","raw":"","form":[{"name":"ad","value":"Gloria Jeanss 2"},{"name":"adres","value":"SDU Batı Kampüsü"},{"name":"imkanlar","value":"Kahve, Çay, Kek, Refresher"},{"name":"enlem","value":"36"},{"name":"boylam","value":"34"},{"name":"gunler1","value":"Pazartesi-Cuma"},{"name":"acilis1","value":"9:10"},{"name":"kapanis1","value":"23:10"},{"name":"kapali1","value":"true"},{"name":"gunler2","value":"Cumartesi"},{"name":"acilis2","value":"10:30"},{"name":"kapanis2","value":"17:30"},{"name":"kapali2","value":"false"}]},"tests":[]},{"_id":"3699e8f4-b6bc-4f00-a20b-bec32eb52d81","colId":"0e9db5e5-dc97-4ab4-bf4b-1bc9273b0090","containerId":"","name":"Yorum Ekle","url":"localhost:3000/api/mekanlar/{{mekanid}}/yorumlar","method":"POST","sortNum":70000,"created":"2022-11-24T18:06:28.972Z","modified":"2022-11-25T19:35:08.067Z","headers":[],"params":[],"body":{"type":"formencoded","raw":"","form":[{"name":"yorumYapan","value":"AU"},{"name":"puan","value":"2"},{"name":"yorumMetni","value":"Kahveler çok kötüü!"}]},"tests":[]},{"_id":"5e5b0e3c-d414-40d4-bba7-bfc4f8f87403","colId":"0e9db5e5-dc97-4ab4-bf4b-1bc9273b0090","containerId":"","name":"Yorum Getir","url":"localhost:3000/api/mekanlar/{{mekanid}}/yorumlar/{{yorumid}}","method":"GET","sortNum":80000,"created":"2022-11-24T18:06:42.033Z","modified":"2022-11-25T19:28:25.721Z","headers":[],"params":[],"tests":[]},{"_id":"4979912e-88b4-497b-bd76-948b27ef6d2a","colId":"0e9db5e5-dc97-4ab4-bf4b-1bc9273b0090","containerId":"","name":"Yorum Güncelle","url":"localhost:3000/api/mekanlar/{{mekanid}}/yorumlar/{{yorumid}}","method":"PUT","sortNum":90000,"created":"2022-11-24T18:06:56.754Z","modified":"2022-11-25T19:29:08.232Z","headers":[],"params":[],"body":{"type":"formencoded","raw":"","form":[{"name":"yorumYapan","value":"Murat"},{"name":"puan","value":"3"},{"name":"yorumMetni","value":"Bu kadar kötü kahve olamazz!!"}]},"tests":[]},{"_id":"68057673-feb8-47e9-9405-bfa367c2611e","colId":"0e9db5e5-dc97-4ab4-bf4b-1bc9273b0090","containerId":"","name":"Yorum Sil","url":"localhost:3000/api/mekanlar/{{mekanid}}/yorumlar/{{yorumid}}","method":"DELETE","sortNum":100000,"created":"2022-11-24T18:07:14.793Z","modified":"2022-11-25T19:29:23.783Z","headers":[],"params":[],"tests":[]},{"_id":"12daf498-8d14-4ae9-b5cd-8a241d4332b9","colId":"0e9db5e5-dc97-4ab4-bf4b-1bc9273b0090","containerId":"","name":"Mekan Sil","url":"localhost:3000/api/mekanlar/{{mekanid}}","method":"DELETE","sortNum":110000,"created":"2022-11-24T18:07:26.825Z","modified":"2022-11-25T19:37:01.313Z","headers":[],"params":[],"tests":[]}]}
